value_fetcher/__init__.py
value_fetcher/aws.py
value_fetcher/base.py
value_fetcher-1.0.3.dist-info/METADATA
value_fetcher-1.0.3.dist-info/WHEEL
value_fetcher-1.0.3.dist-info/licenses/LICENSE
value_fetcher-1.0.3.dist-info/RECORD
