Metadata-Version: 2.3
Name: value-fetcher
Version: 1.0.3
Summary: Fetch a value from various sources, e.g AWS Secrets Manager and SSM Parameter Store
Project-URL: Homepage, https://github.com/voquis/value-fetcher
Project-URL: Issues, https://github.com/voquis/value-fetcher/issues
Author-email: Voquis Limited <opensource@voquis.com>
License-Expression: MIT
License-File: LICENSE
Keywords: configuration,parameters,secrets,values
Classifier: License :: OSI Approved :: MIT License
Classifier: Operating System :: OS Independent
Classifier: Programming Language :: Python :: 3
Requires-Python: >=3.8
Requires-Dist: boto3
Provides-Extra: dev
Requires-Dist: black; extra == 'dev'
Requires-Dist: build; extra == 'dev'
Requires-Dist: flake8; extra == 'dev'
Requires-Dist: moto; extra == 'dev'
Requires-Dist: pylint; extra == 'dev'
Requires-Dist: pytest; extra == 'dev'
Requires-Dist: pytest-cov; extra == 'dev'
Requires-Dist: twine; extra == 'dev'
